fbcli/__init__.py
fbcli/browser.py
fbcli/cli.py
fbcli/editor.py
fbcli/errors.py
fbcli/fb.py
fbcli/ui.py
fbcli-3.2.dist-info/DESCRIPTION.rst
fbcli-3.2.dist-info/METADATA
fbcli-3.2.dist-info/RECORD
fbcli-3.2.dist-info/WHEEL
fbcli-3.2.dist-info/entry_points.txt
fbcli-3.2.dist-info/metadata.json
fbcli-3.2.dist-info/top_level.txt
tests/__init__.py
tests/test_cli.py
tests/test_editor.py
tests/test_fb.py
tests/test_ui.py
