Metadata-Version: 2.0
Name: fbcli
Version: 3.2
Summary: FogBugz command line interface.
Home-page: https://github.com/lbolla/fbcli
Author: Lorenzo Bolla
Author-email: lbolla@gmail.com
License: UNKNOWN
Platform: UNKNOWN
Classifier: Development Status :: 5 - Production/Stable
Classifier: Environment :: Console
Classifier: License :: OSI Approved :: BSD License
Classifier: Natural Language :: English
Classifier: Programming Language :: Python :: 3
Classifier: Operating System :: OS Independent
Requires-Dist: fogbugz (>=1.0.5)
Requires-Dist: lazy-property (==0.0.1)
Requires-Dist: pyyaml (>=3,<4dev)
Requires-Dist: requests (>=2.12.1,<3dev)
Requires-Dist: six
Requires-Dist: tornado (>=4,<5dev)
